doxybook/__init__.py
doxybook/__main__.py
doxybook/cache.py
doxybook/constants.py
doxybook/doxygen.py
doxybook/markdown.py
doxybook/node.py
doxybook/property.py
doxybook/runner.py
doxybook/utils.py
doxybook/xml_parser.py
doxybook/templates/api.jinja
doxybook/templates/detail.jinja
doxybook/templates/footer.jinja
doxybook/templates/table.jinja
doxybook/templates/c/file.jinja
doxybook/templates/cpp/file.jinja
esp_doxybook-0.3.0.dist-info/entry_points.txt
esp_doxybook-0.3.0.dist-info/licenses/LICENSE
esp_doxybook-0.3.0.dist-info/WHEEL
esp_doxybook-0.3.0.dist-info/METADATA
esp_doxybook-0.3.0.dist-info/RECORD
