Metadata-Version: 2.4
Name: esp-doxybook
Version: 0.3.0
Summary: Convert Doxygen XML output into a single-file API reference in Markdown format.
Keywords: doxygen,c,cpp,markdown
Author-email: Fu Hanxi <fuhanxi@espressif.com>
Maintainer-email: Fu Hanxi <fuhanxi@espressif.com>
Requires-Python: >=3.7
Classifier: Development Status :: 4 - Beta
Classifier: License :: OSI Approved :: Apache Software License
Classifier: Programming Language :: Python :: 3.7
Classifier: Programming Language :: Python :: 3.8
Classifier: Programming Language :: Python :: 3.9
Classifier: Programming Language :: Python :: 3.10
Classifier: Programming Language :: Python :: 3.11
Classifier: Programming Language :: Python :: 3.12
Classifier: Programming Language :: Python :: 3.13
License-File: LICENSE
Requires-Dist: Jinja2
Requires-Dist: mkdocs ; extra == "doc"
Requires-Dist: mkdocs-material ; extra == "doc"
Project-URL: Source, https://github.com/espressif/doxybook
Provides-Extra: doc
